video_ethz/__init__.py
video_ethz/cli.py
video_ethz/config.py
video_ethz/downloader.py
video_ethz/utils.py
video_ethz-0.0.5.dist-info/LICENSE
video_ethz-0.0.5.dist-info/METADATA
video_ethz-0.0.5.dist-info/WHEEL
video_ethz-0.0.5.dist-info/entry_points.txt
video_ethz-0.0.5.dist-info/RECORD
